ecstorage/__init__.py
ecstorage/dataframe.py
ecstorage/list.py
ecstorage/rdd.py
ecstorage/mathematics/__init__.py
ecstorage/mathematics/galois.py
ecstorage/mathematics/generator_matrix.py
ecstorage/mathematics/matrix_optimization.py
ec_storage-1.0.0.dist-info/LICENSE.txt
ec_storage-1.0.0.dist-info/METADATA
ec_storage-1.0.0.dist-info/WHEEL
ec_storage-1.0.0.dist-info/top_level.txt
ec_storage-1.0.0.dist-info/RECORD
