Metadata-Version: 2.1
Name: ec-storage
Version: 1.0.0
Summary: ec-storage,it is used to replace the three copy storage strategy of HDFS, so as to save storage space
Home-page: https://github.com/ChoiNgai/EC
Author: CAIWEI
Author-email: caiwei-email@qq.com
License: UNKNOWN
Project-URL: Bug Tracker, https://github.com/ChoiNgai/EC/issues
Platform: UNKNOWN
Classifier: Programming Language :: Python :: 3
Classifier: License :: OSI Approved :: MIT License
Classifier: Operating System :: OS Independent
Requires-Python: >=3.6
License-File: LICENSE.txt
